<?xml version="1.0" encoding="utf-8" ?><dwsync><file name=".DS_Store" server="Macintosh HD/Users/rostheim/Sites/TAS(Live)/" local="3510150520" remote="42164856184" /><file name="cover.css" server="Macintosh HD/Users/rostheim/Sites/TAS(Live)/" local="3508362930" remote="42163068594" /><file name="fonts.css" server="Macintosh HD/Users/rostheim/Sites/TAS(Live)/" local="3513700005" remote="42168405669" /><file name="offcanvas.css" server="Macintosh HD/Users/rostheim/Sites/TAS(Live)/" local="3509582448" remote="59344157296" /><file name="timeline.css" server="Macintosh HD/Users/rostheim/Sites/TAS(Live)/" local="3513879699" remote="55053487251" /><file name=".DS_Store" server="sftp2.woc.noaa.gov//beta.w1.tas.noaa.gov/" local="3510150520" remote="42168610477" /><file name="cover.css" server="sftp2.woc.noaa.gov//beta.w1.tas.noaa.gov/" local="3508362930" remote="42168610480" /><file name="fonts.css" server="sftp2.woc.noaa.gov//beta.w1.tas.noaa.gov/" local="3513700005" remote="42168610481" /><file name="offcanvas.css" server="sftp2.woc.noaa.gov//beta.w1.tas.noaa.gov/" local="3509582448" remote="59348479665" /><file name="table.css" server="sftp2.woc.noaa.gov//beta.w1.tas.noaa.gov/" local="3513804228" remote="42168610482" /><file name="timeline.css" server="sftp2.woc.noaa.gov//beta.w1.tas.noaa.gov/" local="3513879699" remote="55053512371" /><file name="table.css" server="Macintosh HD/Users/rostheim/Sites/TAS(Live)/" local="3513804228" remote="42168509892" /></dwsync>